{
  "users": [
    {
      "id": "1",
      "username": "cankoroot",
      "email": "burakyaldizby@gmail.com",
      "password": "159357",
      "todos": [
        {
          "id": 239,
          "content": "DOST SA",
          "isCompleted": false
        }
      ]
    },
    {
      "username": "gözde",
      "email": "kija.haneul12@gmail.com",
      "password": "159357",
      "todos": [],
      "id": "vNXuzuJnDQ8"
    },
    {
      "username": "cankodeneme",
      "email": "cankodeneme@gmail.com",
      "password": "159357",
      "todos": [
        {
          "id": 402,
          "content": "cankosa",
          "isCompleted": false
        }
      ],
      "id": "Bwd7a1wAWeo"
    }
  ]
}